variation/__init__.py
variation/classify.py
variation/gnomad_vcf_to_protein_variation.py
variation/hgvs_dup_del_mode.py
variation/log_config.py
variation/main.py
variation/normalize.py
variation/query.py
variation/regex.py
variation/to_copy_number_variation.py
variation/to_vrs.py
variation/tokenize.py
variation/translate.py
variation/utils.py
variation/validate.py
variation/vrs_representation.py
variation/classifiers/__init__.py
variation/classifiers/amplification_classifier.py
variation/classifiers/cdna_deletion_classifier.py
variation/classifiers/cdna_delins_classifier.py
variation/classifiers/cdna_insertion_classifier.py
variation/classifiers/cdna_reference_agree_classifier.py
variation/classifiers/cdna_substitution_classifier.py
variation/classifiers/classifier.py
variation/classifiers/genomic_deletion_ambiguous.py
variation/classifiers/genomic_deletion_classifier.py
variation/classifiers/genomic_delins_classifier.py
variation/classifiers/genomic_duplication_ambiguous.py
variation/classifiers/genomic_duplication_classifier.py
variation/classifiers/genomic_insertion_classifier.py
variation/classifiers/genomic_reference_agree_classifier.py
variation/classifiers/genomic_substitution_classifier.py
variation/classifiers/gnomad_vcf_classifier.py
variation/classifiers/hgvs_classifier.py
variation/classifiers/protein_deletion_classifier.py
variation/classifiers/protein_delins_classifier.py
variation/classifiers/protein_insertion_classifier.py
variation/classifiers/protein_reference_agree.py
variation/classifiers/protein_stop_gain_classifier.py
variation/classifiers/protein_substitution_classifier.py
variation/schemas/__init__.py
variation/schemas/app_schemas.py
variation/schemas/classification_response_schema.py
variation/schemas/copy_number_schema.py
variation/schemas/gnomad_vcf_to_protein_schema.py
variation/schemas/hgvs_to_copy_number_schema.py
variation/schemas/normalize_response_schema.py
variation/schemas/service_schema.py
variation_normalizer-0.15.1.dist-info/licenses/LICENSE
variation_normalizer-0.15.1.dist-info/METADATA
variation_normalizer-0.15.1.dist-info/WHEEL
variation_normalizer-0.15.1.dist-info/top_level.txt
variation_normalizer-0.15.1.dist-info/RECORD
