Metadata-Version: 2.4
Name: variation-normalizer
Version: 0.15.1
Summary: VICC normalization routine for variations
Author: Alex Wagner, Kori Kuzma, James Stevenson
License: MIT License
Project-URL: Homepage, https://github.com/cancervariants/variation-normalization
Project-URL: Documentation, https://github.com/cancervariants/variation-normalization
Project-URL: Changelog, https://github.com/cancervariants/variation-normalization/releases
Project-URL: Source, https://github.com/cancervariants/variation-normalization
Project-URL: Bug Tracker, https://github.com/cancervariants/variation-normalization/issues
Classifier: Development Status :: 3 - Alpha
Classifier: Framework :: FastAPI
Classifier: Framework :: Pydantic
Classifier: Framework :: Pydantic :: 2
Classifier: Intended Audience :: Science/Research
Classifier: Intended Audience :: Developers
Classifier: Topic :: Scientific/Engineering :: Bio-Informatics
Classifier: License :: OSI Approved :: MIT License
Classifier: Programming Language :: Python :: 3
Classifier: Programming Language :: Python :: 3.11
Classifier: Programming Language :: Python :: 3.12
Classifier: Programming Language :: Python :: 3.13
Requires-Python: >=3.11
License-File: LICENSE
Requires-Dist: biocommons.seqrepo
Requires-Dist: fastapi
Requires-Dist: uvicorn
Requires-Dist: pydantic==2.*
Requires-Dist: ga4gh.vrs[extras]<3.0,>=2.1.3
Requires-Dist: gene-normalizer>=0.9.0
Requires-Dist: boto3
Requires-Dist: cool-seq-tool~=0.14.2
Requires-Dist: bioutils
Provides-Extra: tests
Requires-Dist: pytest>=6.0; extra == "tests"
Requires-Dist: pytest-cov; extra == "tests"
Requires-Dist: pytest-asyncio; extra == "tests"
Provides-Extra: dev
Requires-Dist: pre-commit>=4.2.0; extra == "dev"
Requires-Dist: ruff==0.12.1; extra == "dev"
Requires-Dist: psycopg2-binary; extra == "dev"
Requires-Dist: jupyter; extra == "dev"
Requires-Dist: ipykernel; extra == "dev"
Dynamic: license-file
